mail/__init__.py
mail/file_meta.py
mail/sender.py
mail_man_cbs-0.1.1.dist-info/METADATA
mail_man_cbs-0.1.1.dist-info/WHEEL
mail_man_cbs-0.1.1.dist-info/top_level.txt
mail_man_cbs-0.1.1.dist-info/RECORD
